README.md
setup.py
green_score/__init__.py
green_score/green.py
green_score/utils.py
green_score.egg-info/PKG-INFO
green_score.egg-info/SOURCES.txt
green_score.egg-info/dependency_links.txt
green_score.egg-info/not-zip-safe
green_score.egg-info/requires.txt
green_score.egg-info/top_level.txt
tests/__init__.py
tests/test_repro.py
tests/test_script.py
tests/time_benchmark.py