Metadata-Version: 2.1
Name: green-score
Version: 0.0.10
Summary: UNKNOWN
Author: Sophie Ostmeier, Jean-Benoit Delbrouck
License: MIT
Platform: UNKNOWN
Classifier: Programming Language :: Python :: 3
Classifier: License :: OSI Approved :: Apache Software License
Classifier: Operating System :: OS Independent
Requires-Python: >=3.9,<=3.10.13
